XinGainianMoniDianlu5YuanDianluXinhaoyuanHeDianyuanFix1/README.md
XinGainianMoniDianlu5YuanDianluXinhaoyuanHeDianyuanFix1/__init__.py
XinGainianMoniDianlu5YuanDianluXinhaoyuanHeDianyuanFix1/__main__.py
XinGainianMoniDianlu5YuanDianluXinhaoyuanHeDianyuanFix1/file.pdf
XinGainianMoniDianlu5YuanDianluXinhaoyuanHeDianyuanFix1/index.html
xin_gainian_moni_dianlu_5_yuan_dianlu_xinhaoyuan_he_dianyuan_fix1-2025.3.24.1.dist-info/METADATA
xin_gainian_moni_dianlu_5_yuan_dianlu_xinhaoyuan_he_dianyuan_fix1-2025.3.24.1.dist-info/WHEEL
xin_gainian_moni_dianlu_5_yuan_dianlu_xinhaoyuan_he_dianyuan_fix1-2025.3.24.1.dist-info/entry_points.txt
xin_gainian_moni_dianlu_5_yuan_dianlu_xinhaoyuan_he_dianyuan_fix1-2025.3.24.1.dist-info/top_level.txt
xin_gainian_moni_dianlu_5_yuan_dianlu_xinhaoyuan_he_dianyuan_fix1-2025.3.24.1.dist-info/RECORD
